boardutils/__init__.py
boardutils/__version__.py
boardutils/api.py
boardutils/sharedstorage.py
boardutils-0.7.2.dist-info/LICENSE
boardutils-0.7.2.dist-info/METADATA
boardutils-0.7.2.dist-info/WHEEL
boardutils-0.7.2.dist-info/top_level.txt
boardutils-0.7.2.dist-info/RECORD
