Metadata-Version: 2.1
Name: boardutils
Version: 0.7.2
Summary: set of utilities to integrate with Board CPM and BI toolkit
Home-page: https://www.board.com
Author: Board International SA
Author-email: info@board.com
License: Usage of the Board API and of boardutils package is granted to Board customers with an active API license
Keywords: board toolkit api utilities
Platform: UNKNOWN
Classifier: Development Status :: 4 - Beta
Classifier: Intended Audience :: Developers
Classifier: Programming Language :: Python :: 3.7
Requires-Python: >=3.7.*
Requires-Dist: requests
Requires-Dist: azure-storage-file
